<?xml version="1.0" encoding="UTF-8"?>
<!DOCTYPE xmeml>

<!--本字幕由 Arctime Pro 2.2.1创建-->
<!--软件网址 arctime.cn-->
<xmeml version="5">
  <sequence id="XML字幕序列">
    <updatebehavior>add</updatebehavior>
    <name>XML字幕序列_25.0p_Subtitle</name>
    <duration>321</duration>
    <rate>
      <ntsc>FALSE</ntsc>
      <timebase>25</timebase>
    </rate>
    <timecode>
      <rate>
        <ntsc>FALSE</ntsc>
        <timebase>25</timebase>
      </rate>
      <string>01:00:00:00</string>
      <frame>90000</frame>
      <source>source</source>
      <displayformat>NDF</displayformat>
    </timecode>
    <in>0</in>
    <out>321</out>
    <width>1920</width>
    <height>1080</height>
    <media>
      <video>
        <format>
          <samplecharacteristics>
            <rate>
              <ntsc>FALSE</ntsc>
              <timebase>25</timebase>
            </rate>
            <width>1920</width>
            <height>1080</height>
            <pixelaspectratio>Square</pixelaspectratio>
            <anamorphic>FALSE</anamorphic>
          </samplecharacteristics>
        </format>
        <track>
          <enabled>TRUE</enabled>
          <locked>FALSE</locked>
        </track>
        <track>
          <clipitem id="Subtitle_IMG_0001.png">
            <!--Hello 这个视频是我的个人简介-->
            <name>Subtitle_IMG_0001.png</name>
            <duration>3251</duration>
            <rate>
              <ntsc>FALSE</ntsc>
              <timebase>25</timebase>
            </rate>
            <in>1500</in>
            <out>1549</out>
            <start>16</start>
            <end>66</end>
            <pixelaspectratio>Square</pixelaspectratio>
            <stillframe>TRUE</stillframe>
            <anamorphic>FALSE</anamorphic>
            <alphatype>straight</alphatype>
            <masterclipid>Subtitle_IMG_0001.png1</masterclipid>
            <file id="Subtitle_IMG_0001">
              <name>Subtitle_IMG_0001.png</name>
              <pathurl>D:/W_BW/source/ff/Subtitle_IMG_0001.png</pathurl>
              <rate>
                <ntsc>FALSE</ntsc>
                <timebase>25</timebase>
              </rate>
              <duration>2</duration>
              <width>1920</width>
              <height>1080</height>
              <media>
                <video>
                  <duration>2</duration>
                  <stillframe>TRUE</stillframe>
                  <samplecharacteristics>
                    <rate>
                      <ntsc>FALSE</ntsc>
                      <timebase>25</timebase>
                    </rate>
                    <width>1920</width>
                    <height>1080</height>
                    <pixelaspectratio>Square</pixelaspectratio>
                    <anamorphic>FALSE</anamorphic>
                  </samplecharacteristics>
                </video>
              </media>
            </file>
            <sourcetrack>
              <mediatype>video</mediatype>
            </sourcetrack>
            <fielddominance>none</fielddominance>
          </clipitem>
          <clipitem id="Subtitle_IMG_0002.png">
            <!--如果你不喜欢这个BGM-->
            <name>Subtitle_IMG_0002.png</name>
            <duration>3251</duration>
            <rate>
              <ntsc>FALSE</ntsc>
              <timebase>25</timebase>
            </rate>
            <in>1500</in>
            <out>1550</out>
            <start>68</start>
            <end>118</end>
            <pixelaspectratio>Square</pixelaspectratio>
            <stillframe>TRUE</stillframe>
            <anamorphic>FALSE</anamorphic>
            <alphatype>straight</alphatype>
            <masterclipid>Subtitle_IMG_0002.png1</masterclipid>
            <file id="Subtitle_IMG_0002">
              <name>Subtitle_IMG_0002.png</name>
              <pathurl>D:/W_BW/source/ff/Subtitle_IMG_0002.png</pathurl>
              <rate>
                <ntsc>FALSE</ntsc>
                <timebase>25</timebase>
              </rate>
              <duration>2</duration>
              <width>1920</width>
              <height>1080</height>
              <media>
                <video>
                  <duration>2</duration>
                  <stillframe>TRUE</stillframe>
                  <samplecharacteristics>
                    <rate>
                      <ntsc>FALSE</ntsc>
                      <timebase>25</timebase>
                    </rate>
                    <width>1920</width>
                    <height>1080</height>
                    <pixelaspectratio>Square</pixelaspectratio>
                    <anamorphic>FALSE</anamorphic>
                  </samplecharacteristics>
                </video>
              </media>
            </file>
            <sourcetrack>
              <mediatype>video</mediatype>
            </sourcetrack>
            <fielddominance>none</fielddominance>
          </clipitem>
          <clipitem id="Subtitle_IMG_0003.png">
            <!--可以按这边的喇叭关掉它-->
            <name>Subtitle_IMG_0003.png</name>
            <duration>3251</duration>
            <rate>
              <ntsc>FALSE</ntsc>
              <timebase>25</timebase>
            </rate>
            <in>1500</in>
            <out>1535</out>
            <start>120</start>
            <end>155</end>
            <pixelaspectratio>Square</pixelaspectratio>
            <stillframe>TRUE</stillframe>
            <anamorphic>FALSE</anamorphic>
            <alphatype>straight</alphatype>
            <masterclipid>Subtitle_IMG_0003.png1</masterclipid>
            <file id="Subtitle_IMG_0003">
              <name>Subtitle_IMG_0003.png</name>
              <pathurl>D:/W_BW/source/ff/Subtitle_IMG_0003.png</pathurl>
              <rate>
                <ntsc>FALSE</ntsc>
                <timebase>25</timebase>
              </rate>
              <duration>2</duration>
              <width>1920</width>
              <height>1080</height>
              <media>
                <video>
                  <duration>2</duration>
                  <stillframe>TRUE</stillframe>
                  <samplecharacteristics>
                    <rate>
                      <ntsc>FALSE</ntsc>
                      <timebase>25</timebase>
                    </rate>
                    <width>1920</width>
                    <height>1080</height>
                    <pixelaspectratio>Square</pixelaspectratio>
                    <anamorphic>FALSE</anamorphic>
                  </samplecharacteristics>
                </video>
              </media>
            </file>
            <sourcetrack>
              <mediatype>video</mediatype>
            </sourcetrack>
            <fielddominance>none</fielddominance>
          </clipitem>
          <clipitem id="Subtitle_IMG_0004.png">
            <!--所有的播放控件在下边的横栏里-->
            <name>Subtitle_IMG_0004.png</name>
            <duration>3251</duration>
            <rate>
              <ntsc>FALSE</ntsc>
              <timebase>25</timebase>
            </rate>
            <in>1500</in>
            <out>1556</out>
            <start>179</start>
            <end>235</end>
            <pixelaspectratio>Square</pixelaspectratio>
            <stillframe>TRUE</stillframe>
            <anamorphic>FALSE</anamorphic>
            <alphatype>straight</alphatype>
            <masterclipid>Subtitle_IMG_0004.png1</masterclipid>
            <file id="Subtitle_IMG_0004">
              <name>Subtitle_IMG_0004.png</name>
              <pathurl>D:/W_BW/source/ff/Subtitle_IMG_0004.png</pathurl>
              <rate>
                <ntsc>FALSE</ntsc>
                <timebase>25</timebase>
              </rate>
              <duration>2</duration>
              <width>1920</width>
              <height>1080</height>
              <media>
                <video>
                  <duration>2</duration>
                  <stillframe>TRUE</stillframe>
                  <samplecharacteristics>
                    <rate>
                      <ntsc>FALSE</ntsc>
                      <timebase>25</timebase>
                    </rate>
                    <width>1920</width>
                    <height>1080</height>
                    <pixelaspectratio>Square</pixelaspectratio>
                    <anamorphic>FALSE</anamorphic>
                  </samplecharacteristics>
                </video>
              </media>
            </file>
            <sourcetrack>
              <mediatype>video</mediatype>
            </sourcetrack>
            <fielddominance>none</fielddominance>
          </clipitem>
          <clipitem id="Subtitle_IMG_0005.png">
            <!--关闭按钮在右上角-->
            <name>Subtitle_IMG_0005.png</name>
            <duration>3251</duration>
            <rate>
              <ntsc>FALSE</ntsc>
              <timebase>25</timebase>
            </rate>
            <in>1500</in>
            <out>1553</out>
            <start>235</start>
            <end>288</end>
            <pixelaspectratio>Square</pixelaspectratio>
            <stillframe>TRUE</stillframe>
            <anamorphic>FALSE</anamorphic>
            <alphatype>straight</alphatype>
            <masterclipid>Subtitle_IMG_0005.png1</masterclipid>
            <file id="Subtitle_IMG_0005">
              <name>Subtitle_IMG_0005.png</name>
              <pathurl>D:/W_BW/source/ff/Subtitle_IMG_0005.png</pathurl>
              <rate>
                <ntsc>FALSE</ntsc>
                <timebase>25</timebase>
              </rate>
              <duration>2</duration>
              <width>1920</width>
              <height>1080</height>
              <media>
                <video>
                  <duration>2</duration>
                  <stillframe>TRUE</stillframe>
                  <samplecharacteristics>
                    <rate>
                      <ntsc>FALSE</ntsc>
                      <timebase>25</timebase>
                    </rate>
                    <width>1920</width>
                    <height>1080</height>
                    <pixelaspectratio>Square</pixelaspectratio>
                    <anamorphic>FALSE</anamorphic>
                  </samplecharacteristics>
                </video>
              </media>
            </file>
            <sourcetrack>
              <mediatype>video</mediatype>
            </sourcetrack>
            <fielddominance>none</fielddominance>
          </clipitem>
          <clipitem id="Subtitle_IMG_0006.png">
            <!--话不多说 我们开始吧-->
            <name>Subtitle_IMG_0006.png</name>
            <duration>3251</duration>
            <rate>
              <ntsc>FALSE</ntsc>
              <timebase>25</timebase>
            </rate>
            <in>1500</in>
            <out>1532</out>
            <start>288</start>
            <end>321</end>
            <pixelaspectratio>Square</pixelaspectratio>
            <stillframe>TRUE</stillframe>
            <anamorphic>FALSE</anamorphic>
            <alphatype>straight</alphatype>
            <masterclipid>Subtitle_IMG_0006.png1</masterclipid>
            <file id="Subtitle_IMG_0006">
              <name>Subtitle_IMG_0006.png</name>
              <pathurl>D:/W_BW/source/ff/Subtitle_IMG_0006.png</pathurl>
              <rate>
                <ntsc>FALSE</ntsc>
                <timebase>25</timebase>
              </rate>
              <duration>2</duration>
              <width>1920</width>
              <height>1080</height>
              <media>
                <video>
                  <duration>2</duration>
                  <stillframe>TRUE</stillframe>
                  <samplecharacteristics>
                    <rate>
                      <ntsc>FALSE</ntsc>
                      <timebase>25</timebase>
                    </rate>
                    <width>1920</width>
                    <height>1080</height>
                    <pixelaspectratio>Square</pixelaspectratio>
                    <anamorphic>FALSE</anamorphic>
                  </samplecharacteristics>
                </video>
              </media>
            </file>
            <sourcetrack>
              <mediatype>video</mediatype>
            </sourcetrack>
            <fielddominance>none</fielddominance>
          </clipitem>
          <enabled>TRUE</enabled>
          <locked>FALSE</locked>
        </track>
      </video>
    </media>
    <ismasterclip>FALSE</ismasterclip>
  </sequence>
</xmeml>
